mystats/__init__.py
mystats/core.py
phantom_mystats-0.1.0.dist-info/METADATA
phantom_mystats-0.1.0.dist-info/WHEEL
phantom_mystats-0.1.0.dist-info/top_level.txt
phantom_mystats-0.1.0.dist-info/RECORD
