Metadata-Version: 2.4
Name: phantom_mystats
Version: 0.1.0
Summary: A custom stats library
Author: Your Name
Requires-Python: >=3.6
Dynamic: author
Dynamic: requires-python
Dynamic: summary
